openpivtk/__init__.py
openpivtk/__main__.py
openpivtk/filters.py
openpivtk/lib.py
openpivtk/modal.py
openpivtk/piv.py
openpivtk/postprocessing.py
openpivtk/preprocess.py
openpivtk/pyprocess.py
openpivtk/scaling.py
openpivtk/smoothn.py
openpivtk/spectral.py
openpivtk/tools.py
openpivtk/validation.py
openpivtk/windef.py
openpivtk/GUI/GUI.py
openpivtk/GUI/Launcher.cmd
openpivtk/GUI/Main_PIV.py
openpivtk/GUI/Main_PIV.ui
openpivtk/GUI/PIV.ico
openpivtk/GUI/PIV_image.jpg
openpivtk/GUI/Splash.jpg
openpivtk/GUI/StyleSheet.qss
openpivtk/GUI/ImageOpener/ImageOpener.py
openpivtk/GUI/ImageOpener/ImageOpener.ui
openpivtk/GUI/ImageOpener/ImageOpenerGUI.py
openpivtk/GUI/ImageOpener/Launcher.cmd
openpivtk/GUI/ImageOpener/SplashFrog.jpg
openpivtk/GUI/ImageOpener/viewerIcon.png
openpivtk/GUI/ImageOpener/__pycache__/ImageOpener.cpython-38.opt-1.pyc
openpivtk/GUI/ImageOpener/__pycache__/ImageOpener.cpython-38.pyc
openpivtk/GUI/ImageOpener/__pycache__/ImageOpener.cpython-39.pyc
openpivtk/GUI/ImageOpener/__pycache__/ImageOpener_GUI.cpython-38.pyc
openpivtk/GUI/Screenshots/FrequencyTab.PNG
openpivtk/GUI/Screenshots/ModalTab.PNG
openpivtk/GUI/Screenshots/ProcessTab.PNG
openpivtk/GUI/Screenshots/ValidationTab.PNG
openpivtk/GUI/Version 0.1/GUI.py
openpivtk/GUI/Version 0.1/PIV.py
openpivtk/GUI/Version 0.1/PIV.ui
openpivtk/GUI/Version 0.2/GUI.py
openpivtk/GUI/Version 0.2/PIV.py
openpivtk/GUI/Version 0.2/PIV.ui
openpivtk/GUI/Version 0.3/GUI.py
openpivtk/GUI/Version 0.3/ImportDialog_Val.py
openpivtk/GUI/Version 0.3/ImportDialog_Val.ui
openpivtk/GUI/Version 0.3/Main_PIV.py
openpivtk/GUI/Version 0.3/Main_PIV.ui
openpivtk/GUI/Version 0.5/GUI.py
openpivtk/GUI/Version 0.5/ImportDialog_Val.py
openpivtk/GUI/Version 0.5/ImportDialog_Val.ui
openpivtk/GUI/Version 0.5/Main_PIV.py
openpivtk/GUI/Version 0.5/Main_PIV.ui
openpivtk/GUI/Version 0.6/GUI.py
openpivtk/GUI/Version 0.6/Main_PIV.py
openpivtk/GUI/Version 0.6/Main_PIV.ui
openpivtk/GUI/__pycache__/GUI.cpython-39.pyc
OpenPIVToolkit-0.2.8.dist-info/LICENSE.txt
OpenPIVToolkit-0.2.8.dist-info/METADATA
OpenPIVToolkit-0.2.8.dist-info/WHEEL
OpenPIVToolkit-0.2.8.dist-info/top_level.txt
OpenPIVToolkit-0.2.8.dist-info/RECORD
