Metadata-Version: 2.1
Name: OpenPIVToolkit
Version: 0.2.8
Summary: Toolkit for PIV Processing and Post-Processing
Home-page: https://github.com/pouya-m/openpiv-toolkit
Author: Pouya Mohtat
Author-email: pouya.m67@gmail.com
License: UNKNOWN
Platform: UNKNOWN
Classifier: Development Status :: 4 - Beta
Classifier: Programming Language :: Python :: 3.7
Classifier: Programming Language :: Python :: 3.8
Classifier: Environment :: Console
Classifier: Environment :: MacOS X
Classifier: Environment :: Win32 (MS Windows)
Classifier: Environment :: X11 Applications
Classifier: Intended Audience :: Science/Research
Classifier: License :: OSI Approved :: GNU General Public License v3 (GPLv3)
Classifier: Natural Language :: English
Classifier: Operating System :: OS Independent
Classifier: Topic :: Scientific/Engineering
Requires-Dist: numpy
Requires-Dist: imageio
Requires-Dist: matplotlib (>=3)
Requires-Dist: scikit-image
Requires-Dist: scipy
Requires-Dist: PySide2
